[{"__type__":"cc.SpriteFrame","content":{"name":"darker_bottom","texture":"c2CvCwFOJFlZEtwtcuG0IE","rect":[0,0,10,294],"offset":[0,0],"originalSize":[10,294],"capInsets":[0,0,0,0]}},[{"__type__":"cc.Prefab","_name":"footer_controller","data":{"__id__":1}},{"__type__":"cc.Node","_name":"footer_controller","_children":[{"__id__":2},{"__id__":3}],"_level":1,"_components":[{"__type__":"3d89cVWk/VPCbCQgAD2+l4u","node":{"__id__":1},"normalFooter":{"__id__":3},"bonusFooter":{"__id__":2}}],"_prefab":{"__type__":"cc.PrefabInfo","root":{"__id__":1},"asset":{"__uuid__":"cegdSgUIxCXY6E5OUkxob7"},"fileId":"15397uYpdFIIw5U+8eLpWT"},"_position":{"__type__":"cc.Vec3","y":-897}},{"__type__":"cc.Node","_name":"footer","_parent":{"__id__":1},"_active":false,"_level":2,"_components":[{"__type__":"cc.Sprite","node":{"__id__":2},"_spriteFrame":{"__uuid__":"842Kljp3hEDoudezZmLWN4"},"_sizeMode":0}],"_prefab":{"__type__":"cc.PrefabInfo","root":{"__id__":1},"asset":{"__uuid__":"cegdSgUIxCXY6E5OUkxob7"},"fileId":"b4SeslVAxCBK/aGnMt27ju"},"_contentSize":{"__type__":"cc.Size","width":1920,"height":515},"_anchorPoint":{"__type__":"cc.Vec2","x":0.5}},{"__type__":"cc.Node","_name":"ui_footer","_parent":{"__id__":1},"_level":2,"_components":[{"__type__":"cc.Sprite","node":{"__id__":3},"_spriteFrame":{"__uuid__":"842Kljp3hEDoudezZmLWN4"},"_sizeMode":0}],"_prefab":{"__type__":"cc.PrefabInfo","root":{"__id__":1},"asset":{"__uuid__":"cegdSgUIxCXY6E5OUkxob7"},"fileId":"dc3Sif0ZZAQLH/Hq8A5H8B"},"_opacity":204,"_contentSize":{"__type__":"cc.Size","width":1920,"height":515},"_anchorPoint":{"__type__":"cc.Vec2","x":0.5}}]]